printk/__init__.py
printk/printk.py
printk-0.3.2.dist-info/METADATA
printk-0.3.2.dist-info/WHEEL
printk-0.3.2.dist-info/top_level.txt
printk-0.3.2.dist-info/RECORD
